{
  "home": {
    "popularProposals":[{"id":"678306df-6d12-4d23-99a5-814db2e82e79","userId":"eca9185b-8d6b-4ee8-8b6b-a47d3410fe1f","content":"It is imperative for all states to take binding steps to curb global climate change.","slug":"it-is-imperative-for-all-states-to-take-binding-steps-to-curb-global-climate-change","status":"Accepted","createdAt":"2019-02-28T10:29:00.250Z","updatedAt":"2019-02-28T10:29:00.253Z","votes":[{"voteKey":"agree","count":5,"qualifications":[{"qualificationKey":"likeIt","count":1,"countVerified":1,"hasQualified":false},{"qualificationKey":"doable","count":2,"countVerified":2,"hasQualified":false},{"qualificationKey":"platitudeAgree","count":0,"countVerified":0,"hasQualified":false}],"hasVoted":false},{"voteKey":"disagree","count":0,"qualifications":[{"qualificationKey":"noWay","count":0,"countVerified":0,"hasQualified":false},{"qualificationKey":"impossible","count":0,"countVerified":0,"hasQualified":false},{"qualificationKey":"platitudeDisagree","count":0,"countVerified":0,"hasQualified":false}],"hasVoted":false},{"voteKey":"neutral","count":1,"qualifications":[{"qualificationKey":"doNotUnderstand","count":0,"countVerified":0,"hasQualified":false},{"qualificationKey":"noOpinion","count":0,"countVerified":0,"hasQualified":false},{"qualificationKey":"doNotCare","count":0,"countVerified":0,"hasQualified":false}],"hasVoted":false}],"context":{"operation":null,"source":null,"location":null,"question":null,"getParameters":[]},"trending":null,"labels":[],"author":{"firstName":"Péter","organisationName":null,"organisationSlug":null,"postalCode":null,"age":52,"avatarUrl":null},"organisations":[],"country":"FR","language":"fr","themeId":null,"tags":[],"myProposal":false,"idea":null,"question":{"questionId":"56f90731-798b-45e1-bd88-321c99fcd8bd","slug":"weuropeanround-fr","wording":{"title":"WeEuropeans Round","question":"Comment réinventer l'Europe, concrètement ?"},"startDate":null,"endDate":null},"operationId":"d63352a6-fe0a-41e5-85fb-334d30bcd778","proposalKey":"45313fcccc11c57c1460e72295c119bc408977809991c03ae13a512f021a00c13bcc410e2557a4106f69d42a5e493a250814515466d45e548902c12b30d62c41"},{"id":"e07c2d96-d75c-4ab1-88db-fabc9ce9ba51","userId":"98e759c8-d1be-4f2d-a028-d1c169509d64","content":"Il faut tester pour mep","slug":"il-faut-tester-pour-mep","status":"Accepted","createdAt":"2019-07-02T09:47:36.669Z","updatedAt":"2019-07-02T09:58:16.714Z","votes":[{"voteKey":"agree","count":5,"qualifications":[{"qualificationKey":"likeIt","count":3,"countVerified":3,"hasQualified":false},{"qualificationKey":"doable","count":0,"countVerified":0,"hasQualified":false},{"qualificationKey":"platitudeAgree","count":0,"countVerified":0,"hasQualified":false}],"hasVoted":false},{"voteKey":"disagree","count":1,"qualifications":[{"qualificationKey":"noWay","count":0,"countVerified":0,"hasQualified":false},{"qualificationKey":"impossible","count":0,"countVerified":0,"hasQualified":false},{"qualificationKey":"platitudeDisagree","count":0,"countVerified":0,"hasQualified":false}],"hasVoted":false},{"voteKey":"neutral","count":0,"qualifications":[{"qualificationKey":"doNotUnderstand","count":0,"countVerified":0,"hasQualified":false},{"qualificationKey":"noOpinion","count":0,"countVerified":0,"hasQualified":false},{"qualificationKey":"doNotCare","count":0,"countVerified":0,"hasQualified":false}],"hasVoted":false}],"context":{"operation":"022e3abb-25d1-4c47-946d-38f901041b4e","source":"core","location":"page-operation aa35389b-7ba7-44a8-811c-e3a7ee3502fc","question":"aa35389b-7ba7-44a8-811c-e3a7ee3502fc","getParameters":[]},"trending":null,"labels":[],"author":{"firstName":"julie","organisationName":null,"organisationSlug":null,"postalCode":"75053","age":60,"avatarUrl":"https://lh4.googleusercontent.com/-XY-Xu0HbFmU/AAAAAAAAAAI/AAAAAAAAAA4/RONAro0CubA/s96-c/photo.jpg"},"organisations":[],"country":"FR","language":"fr","themeId":null,"tags":[{"tagId":"2b820c69-cec5-4481-bc83-ed748ce8f69c","label":"entreprise","display":true},{"tagId":"2db0f8e3-ef7b-48d4-a1e6-d03edff7f7d6","label":"société","display":true}],"myProposal":false,"idea":"7f378d2e-d867-4226-8574-fb078a2de8f1","question":{"questionId":"aa35389b-7ba7-44a8-811c-e3a7ee3502fc","slug":"handicap","wording":{"title":"Une vraie place pour les personnes handicapées","question":"Comment la société peut-elle garantir une vraie place aux personnes handicapées ?"},"startDate":"2019-05-15T00:00:00.000Z","endDate":"2019-08-31T00:00:00.000Z"},"operationId":"022e3abb-25d1-4c47-946d-38f901041b4e","proposalKey":"91dd81a8e26292cbb5ceae1f78c01a390893e3056de44b5c433861388be76f9bfc45b9cf6a721478ac88e72cbe5ef62f768412c3505a5d6a57286a415fe4bd66"}],"controverseProposals":[{"id":"2325ca6b-39ac-4857-af28-79bcedc21dcf","userId":"a5d08e79-756b-49d6-b93b-7eedc562d6f0","content":"You should try to replace plastic as much as possible and maybe start packing not everything 3 times.","slug":"you-should-try-to-replace-plastic-as-much-as-possible-and-maybe-start-packing-not-everything-3-times","status":"Accepted","createdAt":"2019-02-28T10:28:42.249Z","updatedAt":"2019-02-28T10:28:42.253Z","votes":[{"voteKey":"agree","count":4,"qualifications":[{"qualificationKey":"likeIt","count":3,"countVerified":3,"hasQualified":false},{"qualificationKey":"doable","count":0,"countVerified":0,"hasQualified":false},{"qualificationKey":"platitudeAgree","count":0,"countVerified":0,"hasQualified":false}],"hasVoted":false},{"voteKey":"disagree","count":3,"qualifications":[{"qualificationKey":"noWay","count":1,"countVerified":1,"hasQualified":false},{"qualificationKey":"impossible","count":0,"countVerified":0,"hasQualified":false},{"qualificationKey":"platitudeDisagree","count":0,"countVerified":0,"hasQualified":false}],"hasVoted":false},{"voteKey":"neutral","count":0,"qualifications":[{"qualificationKey":"doNotUnderstand","count":0,"countVerified":0,"hasQualified":false},{"qualificationKey":"noOpinion","count":0,"countVerified":0,"hasQualified":false},{"qualificationKey":"doNotCare","count":0,"countVerified":0,"hasQualified":false}],"hasVoted":false}],"context":{"operation":null,"source":null,"location":null,"question":null,"getParameters":[]},"trending":null,"labels":[],"author":{"firstName":"Sandra","organisationName":null,"organisationSlug":null,"postalCode":null,"age":32,"avatarUrl":null},"organisations":[],"country":"FR","language":"fr","themeId":null,"tags":[],"myProposal":false,"idea":null,"question":{"questionId":"56f90731-798b-45e1-bd88-321c99fcd8bd","slug":"weuropeanround-fr","wording":{"title":"WeEuropeans Round","question":"Comment réinventer l'Europe, concrètement ?"},"startDate":null,"endDate":null},"operationId":"d63352a6-fe0a-41e5-85fb-334d30bcd778","proposalKey":"0594708564a64090d38ecc48dc2a08a1652c8bb4289ba9ae3f84b9d2ab16f091b3fdd4b5ad78629df9c1baf6659e9ee97a8d19fe9cf4fbc1666cba3c9c337f5d"},{"id":"f9fdb454-34c6-44c9-8c3e-6177f23c1a67","userId":"10ca5b7f-9183-4b0e-8be0-c2adc0dc3a91","content":"Il faut permettre aux enfants handicapés d'intégrer des classes communes aux enfants non handicapés ","slug":"il-faut-permettre-aux-enfants-handicapes-d-integrer-des-classes-communes-aux-enfants-non-handicapes","status":"Accepted","createdAt":"2019-05-20T16:07:49.330Z","updatedAt":"2019-05-20T16:07:49.345Z","votes":[{"voteKey":"agree","count":10,"qualifications":[{"qualificationKey":"likeIt","count":3,"countVerified":3,"hasQualified":false},{"qualificationKey":"doable","count":0,"countVerified":0,"hasQualified":false},{"qualificationKey":"platitudeAgree","count":0,"countVerified":0,"hasQualified":false}],"hasVoted":false},{"voteKey":"disagree","count":10,"qualifications":[{"qualificationKey":"noWay","count":1,"countVerified":1,"hasQualified":false},{"qualificationKey":"impossible","count":0,"countVerified":0,"hasQualified":false},{"qualificationKey":"platitudeDisagree","count":0,"countVerified":0,"hasQualified":false}],"hasVoted":false},{"voteKey":"neutral","count":14,"qualifications":[{"qualificationKey":"doNotUnderstand","count":0,"countVerified":0,"hasQualified":false},{"qualificationKey":"noOpinion","count":0,"countVerified":0,"hasQualified":false},{"qualificationKey":"doNotCare","count":0,"countVerified":0,"hasQualified":false}],"hasVoted":false}],"context":{"operation":null,"source":null,"location":null,"question":null,"getParameters":[]},"trending":null,"labels":[],"author":{"firstName":"Victor","organisationName":null,"organisationSlug":null,"postalCode":null,"age":45,"avatarUrl":null},"organisations":[],"country":"FR","language":"fr","themeId":null,"tags":[],"myProposal":false,"idea":null,"question":{"questionId":"aa35389b-7ba7-44a8-811c-e3a7ee3502fc","slug":"handicap","wording":{"title":"Une vraie place pour les personnes handicapées","question":"Comment la société peut-elle garantir une vraie place aux personnes handicapées ?"},"startDate":"2019-05-15T00:00:00.000Z","endDate":"2019-08-31T00:00:00.000Z"},"operationId":"022e3abb-25d1-4c47-946d-38f901041b4e","proposalKey":"5521ab86bb9b2feb18531558a7d1b7c98f57cac08949abc9f4931adf3937df29fdcba5be011326b560654a7884fb4356665cfad58ca9063cd7efb26d019c32d2"}],"businessConsultations":[{"theme":{"gradientStart":"#1657ec","gradientEnd":"#1657ec"},"startDate":"2019-03-05T00:00:00.000Z","endDate":"2019-04-25T00:00:00.000Z","slug":"economiebienveillante","aboutUrl":"https://about.make.org/about-economiebienveillante","question":"Comment agir pour rendre notre économie plus bienveillante ?"},{"theme":{"gradientStart":"#7DB7E3","gradientEnd":"#5DA113"},"startDate":"2018-10-18T00:00:00.000Z","endDate":"2019-03-01T00:00:00.000Z","slug":"european-digital-champions","aboutUrl":"https://about.make.org/about-european-digital-champions","question":"Comment faire émerger des champions européens du numérique ? "},{"theme":{"gradientStart":"#fea8fe","gradientEnd":"#35bfff"},"startDate":"2018-10-07T00:00:00.000Z","endDate":"2019-01-03T00:00:00.000Z","slug":"jeunesse-hautsdefrance","aboutUrl":"https://about.make.org/about-jeunesse-hautsdefrance","question":"Comment vous aider à construire votre avenir en Hauts-de-France ?"},{"theme":{"gradientStart":"#673475","gradientEnd":"#673475"},"startDate":"2018-07-01T22:00:00.000Z","endDate":"2018-03-01T00:00:00.000Z","slug":"lpae","aboutUrl":"https://about.make.org/about-lpae","question":"La Parole aux Etudiants"},{"theme":{"gradientStart":"#f5515f","gradientEnd":"#9f041b"},"startDate":"2019-06-17T22:00:00.000Z","endDate":"2019-09-23T22:00:00.000Z","slug":"medias-citoyens","aboutUrl":"https://about.make.org/medias-citoyens","question":"Comment les médias peuvent-ils améliorer la société ? "},{"theme":{"gradientStart":"#000000","gradientEnd":"#000000"},"startDate":"2019-01-23T00:00:00.000Z","endDate":"2012-03-23T00:00:00.000Z","slug":"business-question","aboutUrl":null,"question":"business question"},{"theme":{"gradientStart":"#ff5757","gradientEnd":"#ffb662"},"startDate":"2019-04-26T00:00:00.000Z","endDate":"2019-07-20T00:00:00.000Z","slug":"prevention-jeunes","aboutUrl":"https://about.make.org/about-prevention-jeunes","question":"Comment inciter les jeunes à mieux prendre soin de leur santé ?"},{"theme":{"gradientStart":"#000000","gradientEnd":"#000000"},"startDate":"2018-10-21T00:00:00.000Z","endDate":"2019-02-01T00:00:00.000Z","slug":"villededemain","aboutUrl":"https://about.make.org/about-villededemain","question":"La ville de demain"}],"featuredConsultations":[{"questionId":"e0066ec1-6128-4900-a470-e34e37acbecd","questionSlug":"medias-citoyens","title":"Comment les médias peuvent-ils améliorer la société ?","description":null,"landscapePicture":"images/homepage/medias-citoyens.jpg","portraitPicture":"images/homepage/medias-citoyens.jpg","altPicture":"Aller sur la page de la consultation : Comment les médias peuvent-ils améliorer la société ?","label":"ACTUALITÉ","buttonLabel":"PARTICIPEZ","internalLink":"CONSULTATION","externalLink":null,"slot":1},{"questionId":"aa35389b-7ba7-44a8-811c-e3a7ee3502fc","questionSlug":"handicap","title":"Comment la société peut-elle garantir une vraie place aux personnes handicapées ?","description":"MAKE.ORG et ses partenaires ont lancé une consultation pour garantir une vraie place aux personnes handicapées. Votez, proposez, agissez !","landscapePicture":"http://www.ifrav.fr/wp-content/uploads/2018/03/%C3%A9quipe-make-org-737x415.jpg","portraitPicture":"http://www.ifrav.fr/wp-content/uploads/2018/03/%C3%A9quipe-make-org-737x415.jpg","altPicture":"Aller sur la page de la consultation : Comment la société peut-elle garantir une vraie place aux personnes handicapées ?","label":"GRANDE CAUSE","buttonLabel":"PARTICIPEZ","internalLink":"CONSULTATION","externalLink":null,"slot":2},{"questionId":null,"questionSlug":null,"title":"b","description":"b","landscapePicture":"b","portraitPicture":"b","altPicture":"b","label":"b","buttonLabel":"b","internalLink":null,"externalLink":"a","slot":3}],"currentConsultations":[{"questionId":"3548602e-7592-4ecc-9825-6ce80870cab9","questionSlug":"chance-aux-jeunes","picture":"https://uploads-ssl.webflow.com/59833d390a24e50001b873d8/5d3717d524fd2ab79da43b59_chance%20aux%20jeunes.svg","altPicture":"Une chance pour chaque jeune","description":"Découvrez les idées qui ont émergé de notre consultation.","linkLabel":"Découvrir","internalLink":null,"externalLink":"https://about.make.org/about-chance-aux-jeunes","proposalsNumber":1367,"startDate":null,"endDate":null},{"questionId":"7108965b-0229-4e00-b313-abb491dee6ac","questionSlug":"culture","picture":"https://uploads-ssl.webflow.com/59833d390a24e50001b873d8/5d3717d80e8fa550ba5a52e1_culture.svg","altPicture":"Comment rendre la Culture accessible à tous ?","description":"Découvrez les idées qui ont émergé de notre consultation.","linkLabel":"Découvrir les résultats","internalLink":null,"externalLink":"https://about.make.org/about-culture","proposalsNumber":1850,"startDate":null,"endDate":null},{"questionId":"f85c0099-db6c-471c-a771-5baf5bd57d8d","questionSlug":"gilets-jaunes","picture":"https://uploads-ssl.webflow.com/59833d390a24e50001b873d8/5d3717d9d2bab608e67e1f43_grand%20de%CC%81bat.svg","altPicture":"Grand Débat National","description":"LA PREMIÈRE SYNTHÈSE FAITE PAR LES FRANÇAIS EUX-MÊMES","linkLabel":"","internalLink":null,"externalLink":"https://about.make.org/grande-consultation-nationale-quelles-sont-vos-propositions","proposalsNumber":4,"startDate":null,"endDate":null},{"questionId":"c27b4109-68d8-4e12-91e2-eebb563f0ce8","questionSlug":"vff","picture":"https://uploads-ssl.webflow.com/59833d390a24e50001b873d8/5d3717d824fd2a204fa43b6a_vff.svg","altPicture":"Stop aux violences faîtes aux femmes","description":"Découvrez l'état d'avancement de nos actions.","linkLabel":"Voir le plan d'actions","internalLink":null,"externalLink":"https://about.make.org/about-vff","proposalsNumber":3244,"startDate":null,"endDate":null},{"questionId":"0054db0a-9ae0-402b-9189-b88c457d501e","questionSlug":"aines","picture":"https://uploads-ssl.webflow.com/59833d390a24e50001b873d8/5d3717d48825e02f0866aca3_aines.svg","altPicture":"Comment prendre soin de nos aînés ?","description":"Découvrez les idées qui ont émergé de notre consultation sur les aînés.","linkLabel":"","internalLink":null,"externalLink":"https://about.make.org/about-aines","proposalsNumber":7281,"startDate":null,"endDate":null},{"questionId":"b8678934-f35a-4420-bac4-a5c57b0f09d8","questionSlug":"mieux-vivre-ensemble","picture":"https://uploads-ssl.webflow.com/59833d390a24e50001b873d8/5d3717d810a6d045b4c1ca92_mieux%20vivre%20ensemble.svg","altPicture":"Mieux vivre ensemble","description":"Découvrez les résultats de la consultation.","linkLabel":"","internalLink":null,"externalLink":"https://about.make.org/about-mieux-vivre-ensemble","proposalsNumber":1828,"startDate":null,"endDate":null}]
  }
}